endb.py
endb_console.py
endb-0.2.0b1.dist-info/METADATA
endb-0.2.0b1.dist-info/WHEEL
endb-0.2.0b1.dist-info/entry_points.txt
endb-0.2.0b1.dist-info/top_level.txt
endb-0.2.0b1.dist-info/RECORD
