Metadata-Version: 2.1
Name: endb
Version: 0.2.0b1
Summary: Endatabas Python Client
Author-email: Endatabas <hello@endatabas.com>
License: MIT License
Project-URL: Homepage, https://www.endatabas.com/
Project-URL: Repository, https://github.com/endatabas/endb.git
Project-URL: Documentation, https://docs.endatabas.com/reference/clients
Keywords: endatabas,endb,immutable,sql,database
Classifier: Programming Language :: Python :: 3
Classifier: License :: OSI Approved :: MIT License
Classifier: Operating System :: OS Independent
Classifier: Development Status :: 4 - Beta
Requires-Python: >=3.10
Provides-Extra: pyarrow
Requires-Dist: pyarrow >=15 ; extra == 'pyarrow'
Provides-Extra: websockets
Requires-Dist: websockets >=12 ; extra == 'websockets'
